myrepos/__init__.py
myrepos/repos.py
my_repos-0.1.1.dist-info/entry_points.txt
my_repos-0.1.1.dist-info/WHEEL
my_repos-0.1.1.dist-info/METADATA
my_repos-0.1.1.dist-info/RECORD
