Metadata-Version: 2.1
Name: my-repos
Version: 0.1.1
Summary: Keep an offline mirror of some git repositories
License: LGPL
Author: xtofl
Author-email: kristoffel.pirard@gmail.com
Requires-Python: >=3.8,<4.0
Classifier: License :: Other/Proprietary License
Classifier: Programming Language :: Python :: 3
Classifier: Programming Language :: Python :: 3.10
Classifier: Programming Language :: Python :: 3.8
Classifier: Programming Language :: Python :: 3.9
Requires-Dist: click (>=8.0.4,<9.0.0)
